[{"id":"2035b979d8e6bf5f0fb0258ca624fe8f","from":"Unknown","from_email":"jpm6929@aol.com","to":"jeeproject@yahoo.com","to_list":[{"name":"jeeproject@yahoo.com","email":"jeeproject@yahoo.com"}],"cc_list":[],"subject":"Our future","date":"2007-09-12T22:33:54.000Z","formatted_date":"Sep 12, 2007","formatted_time":"10:33 PM","body":"Dear Jeffrey,\nI am recovering now of two mayor issues, my things and our conversation.All I want to tell you is that we should try to make out of this the most positive situation. Count with me on evry aspect of this process. We will turn it arround.J.P.\n________________________________________________________________________\nEmail and AIM finally together. You've gotta check out free AOL Mail! - http://mail.aol.com\n","body_html":"<FONT face=\"Arial, Helvetica, sans-serif\">Dear Jeffrey,<br>\nI am recovering now of two mayor issues, my things and our conversation.All I want to tell you is that we should try to make out of this the most positive situation. Count with me on evry aspect of this process. We will turn it arround.J.P.</FONT><div class=\"AOLPromoFooter\">\n<hr style=\"margin-top:10px;\" />\nEmail and AIM finally together. You've gotta check out free <a href=\"http://o.aolcdn.com/cdn.webmail.aol.com/mailtour/aol/en-us/index.htm?ncid=AOLAOF00020000000970\" target=\"_blank\">AOL Mail</a>!<br/>\n</div>\n","is_from_epstein":false,"attachments":0,"avatar_color":"#db4437","stars":6,"is_redacted":false}]