[{"id":"3a4d7992cd4ffaf321d1ba1306260a89","from":"J. Epstein","from_email":"jeeproject@yahoo.com","to":"Marvin Minsky","to_list":[{"name":"Marvin Minsky","email":"minsky@media.mit.edu"}],"cc_list":[],"subject":"Re:","date":"2007-11-04T15:36:34.000Z","formatted_date":"Nov 4, 2007","formatted_time":"3:36 PM","body":"your call, I don't know him\n\n----- Original Message ----\nFrom: Marvin Minsky <minsky@media.mit.edu>\nTo: J. Epstein <jeeproject@yahoo.com>\nSent: Saturday, November 3, 2007 1:40:23 PM\nSubject: \n\nI need to ask you if you would recommend inviting Mike Dubno to the  \nplanning discussion on Nov 17.\nHe would like to come, but my colleagues don't want anyone there that  \nthey don't already know.\n","body_html":"<p>your call, I don&#39;t know him</p>\n<p>----- Original Message ----<br>From: Marvin Minsky <a href=\"mailto:minsky@media.mit.edu\">minsky@media.mit.edu</a><br>To: J. Epstein <a href=\"mailto:jeeproject@yahoo.com\">jeeproject@yahoo.com</a><br>Sent: Saturday, November 3, 2007 1:40:23 PM<br>Subject: </p>\n<p>I need to ask you if you would recommend inviting Mike Dubno to the<br>planning discussion on Nov 17.<br>He would like to come, but my colleagues don&#39;t want anyone there that<br>they don&#39;t already know.</p>\n","is_from_epstein":true,"attachments":0,"avatar_color":"#9c27b0","stars":5,"is_redacted":false}]