[{"id":"f33525d9be27ffd10b67046bb9b84661","from":"gmax","from_email":"gmax1@ellmax.com","to":"J J","to_list":[{"name":"J J","email":"jeeproject@yahoo.com"}],"cc_list":[],"subject":"<no subject>","date":"2008-06-21T16:42:34.000Z","formatted_date":"Jun 21, 2008","formatted_time":"4:42 PM","body":"Did you see Gossman house sold for a record?\n","body_html":"<HTML>\n<HEAD>\n\n</HEAD>\n<BODY>\n<FONT FACE=\"Calibri, Verdana, Helvetica, Arial\"><SPAN STYLE='font-size:13pt'>Did you see Gossman house sold for a record?</SPAN></FONT>\n</BODY>\n</HTML>\n\n","is_from_epstein":false,"attachments":0,"avatar_color":"#ff6d01","stars":3,"is_redacted":false}]