[{"id":"740","from":"Lesley Groff","from_email":"\u2588\u2588\u2588\u2588\u2588\u2588\u2588\u2588\u2588\u2588\u2588\u2588","to":"Jeffrey Epstein","to_list":[{"name":"Jeffrey Epstein","email":"Jeffrey Epstein"}],"cc_list":[{"name":"jeevacation@gmail.com","email":"jeevacation@gmail.com"}],"subject":"Fwd: INVITE THE NY OBSERVER 25TH ANNIVERSARY","date":"2013-02-28T01:33:00.000Z","formatted_date":"Feb 28, 2013","formatted_time":"1:33 AM","body":"Sent from my iPhone\n\nBegin forwarded message:","body_html":"<p>Sent from my iPhone</p>\n<p>Begin forwarded message:</p>\n","is_from_epstein":false,"attachments":1,"avatar_color":"#db4437","stars":13,"is_redacted":true},{"id":"741","from":"\u2588","from_email":"\u2588","to":"\u2588","to_list":[{"name":"\u2588","email":"\u2588"}],"cc_list":[],"subject":"Fwd: INVITE THE NY OBSERVER 25TH ANNIVERSARY","date":"2013-02-27T14:55:00.000Z","formatted_date":"Feb 27, 2013","formatted_time":"2:55 PM","body":"Dear Mr. Jeffrey Epstein\n\nJared Kushner, New York's youngest powerhouse publisher, is celebrating the 25th Anniversary of the New York Observer on Thursday, March 14th.\n\nMayor Michael Bloomberg will be by his side to toast you all.\n\nThe Observer is honoring those who have defined and shaped New York since 1987. They are celebrating the cities best, brightest and most influential in culture, media and finance. The salmon pink pages are revered among New York's elite as the preeminent voice on power.\n\nThe celebration is going to be one of those quintessential New York nights. We are looking forward to seeing you.\n\nxoxo,\nPeggy\n\nJared Kushner, Publisher Joseph Meyer, CEO\n\nCory Booker Arthur Carter Georgina Chapman Katie Couric Lauren Santo Domingo\nLarry Gagosian Mariska Hargitay Carolina Herrera Katie Holmes Woody Johnson\nPeter Kaplan Comm. Ray Kelly Ken Kurson Matt Lauer Blake Lively Terry Lundgren\nPeter Martins Cynthia McFadden Sean Parker Ron O. Perelman Stephen Schwarzman\nLara Spencer Steve Tisch Donald Trump Ivanka Trump Harvey Weinstein George C. Wolfe","body_html":"<p>Dear Mr. Jeffrey Epstein</p>\n<p>Jared Kushner, New York&#39;s youngest powerhouse publisher, is celebrating the 25th Anniversary of the New York Observer on Thursday, March 14th.</p>\n<p>Mayor Michael Bloomberg will be by his side to toast you all.</p>\n<p>The Observer is honoring those who have defined and shaped New York since 1987. They are celebrating the cities best, brightest and most influential in culture, media and finance. The salmon pink pages are revered among New York&#39;s elite as the preeminent voice on power.</p>\n<p>The celebration is going to be one of those quintessential New York nights. We are looking forward to seeing you.</p>\n<p>xoxo,<br>Peggy</p>\n<p>Jared Kushner, Publisher Joseph Meyer, CEO</p>\n<p>Cory Booker Arthur Carter Georgina Chapman Katie Couric Lauren Santo Domingo<br>Larry Gagosian Mariska Hargitay Carolina Herrera Katie Holmes Woody Johnson<br>Peter Kaplan Comm. Ray Kelly Ken Kurson Matt Lauer Blake Lively Terry Lundgren<br>Peter Martins Cynthia McFadden Sean Parker Ron O. Perelman Stephen Schwarzman<br>Lara Spencer Steve Tisch Donald Trump Ivanka Trump Harvey Weinstein George C. Wolfe</p>\n","is_from_epstein":false,"attachments":0,"avatar_color":"#db4437","stars":19,"is_redacted":true}]