[{"id":"1361","from":"Kathy Ruemmler","from_email":"\u2588\u2588\u2588\u2588\u2588\u2588\u2588\u2588\u2588\u2588\u2588\u2588\u2588\u2588\u2588\u2588\u2588\u2588\u2588\u2588","to":"jeffrey E.","to_list":[{"name":"jeffrey E.","email":"jeevacation@gmail.com"}],"cc_list":[],"subject":"Re: Fwd:","date":"2014-09-20T00:17:00.000Z","formatted_date":"Sep 20, 2014","formatted_time":"12:17 AM","body":"I have so much more info to tell you on Sunday.","body_html":"<p>I have so much more info to tell you on Sunday.</p>\n","is_from_epstein":false,"attachments":0,"avatar_color":"#f39c12","stars":6,"is_redacted":true},{"id":"1362","from":"jeffrey E.","from_email":"jeevacation@gmail.com","to":"Kathy Ruemmler","to_list":[{"name":"Kathy Ruemmler","email":"\u2588\u2588\u2588\u2588\u2588\u2588\u2588\u2588\u2588\u2588\u2588\u2588\u2588\u2588\u2588\u2588\u2588\u2588\u2588\u2588"}],"cc_list":[],"subject":"Re: Fwd:","date":"2014-09-19T20:16:00.000Z","formatted_date":"Sep 19, 2014","formatted_time":"8:16 PM","body":"how much and who pays now?","body_html":"<p>how much and who pays now?</p>\n","is_from_epstein":true,"attachments":0,"avatar_color":"#db4437","stars":0,"is_redacted":true},{"id":"1363","from":"Kathy Ruemmler","from_email":"\u2588\u2588\u2588\u2588\u2588\u2588\u2588\u2588\u2588\u2588\u2588\u2588\u2588\u2588\u2588\u2588\u2588\u2588\u2588\u2588","to":"jeffrey E.","to_list":[{"name":"jeffrey E.","email":"jeevacation@gmail.com"}],"cc_list":[],"subject":"Re: Fwd:","date":"2014-09-19T17:35:00.000Z","formatted_date":"Sep 19, 2014","formatted_time":"5:35 PM","body":"I will. The rent on the apartment is significantly more than the monthly salary.","body_html":"<p>I will. The rent on the apartment is significantly more than the monthly salary.</p>\n","is_from_epstein":false,"attachments":0,"avatar_color":"#f39c12","stars":0,"is_redacted":true},{"id":"1364","from":"jeffrey E.","from_email":"jeevacation@gmail.com","to":"Kathy Ruemmler","to_list":[{"name":"Kathy Ruemmler","email":"\u2588\u2588\u2588\u2588\u2588\u2588\u2588\u2588\u2588\u2588\u2588\u2588\u2588\u2588\u2588\u2588\u2588\u2588\u2588\u2588"}],"cc_list":[],"subject":"Re: Fwd:","date":"2014-09-19T17:34:00.000Z","formatted_date":"Sep 19, 2014","formatted_time":"5:34 PM","body":"no need to. call eric and get a data point","body_html":"<p>no need to. call eric and get a data point</p>\n","is_from_epstein":true,"attachments":0,"avatar_color":"#db4437","stars":0,"is_redacted":true},{"id":"1365","from":"Kathy Ruemmler","from_email":"\u2588\u2588\u2588\u2588\u2588\u2588\u2588\u2588\u2588\u2588\u2588\u2588\u2588\u2588\u2588\u2588\u2588\u2588\u2588\u2588","to":"jeffrey E.","to_list":[{"name":"jeffrey E.","email":"jeevacation@gmail.com"}],"cc_list":[],"subject":"Re: Fwd:","date":"2014-09-19T17:23:00.000Z","formatted_date":"Sep 19, 2014","formatted_time":"5:23 PM","body":"I don't want to give up my apartment in NY.","body_html":"<p>I don&#39;t want to give up my apartment in NY.</p>\n","is_from_epstein":false,"attachments":0,"avatar_color":"#f39c12","stars":1,"is_redacted":true},{"id":"1366","from":"Kathy Ruemmler","from_email":"\u2588\u2588\u2588\u2588\u2588\u2588\u2588\u2588\u2588\u2588\u2588\u2588\u2588\u2588\u2588\u2588\u2588\u2588\u2588\u2588","to":"jeffrey E.","to_list":[{"name":"jeffrey E.","email":"jeevacation@gmail.com"}],"cc_list":[],"subject":"Re: Fwd:","date":"2014-09-19T17:18:00.000Z","formatted_date":"Sep 19, 2014","formatted_time":"5:18 PM","body":"Good advice.","body_html":"<p>Good advice.</p>\n","is_from_epstein":false,"attachments":0,"avatar_color":"#f39c12","stars":0,"is_redacted":true},{"id":"1367","from":"jeffrey E.","from_email":"jeevacation@gmail.com","to":"Kathy Ruemmler","to_list":[{"name":"Kathy Ruemmler","email":"\u2588\u2588\u2588\u2588\u2588\u2588\u2588\u2588\u2588\u2588\u2588\u2588\u2588\u2588\u2588\u2588\u2588\u2588\u2588\u2588"}],"cc_list":[],"subject":"Re: Fwd:","date":"2014-09-19T17:15:00.000Z","formatted_date":"Sep 19, 2014","formatted_time":"5:15 PM","body":"lets see how you feel sunday","body_html":"<p>lets see how you feel sunday</p>\n","is_from_epstein":true,"attachments":0,"avatar_color":"#db4437","stars":0,"is_redacted":true},{"id":"1368","from":"Kathy Ruemmler","from_email":"\u2588\u2588\u2588\u2588\u2588\u2588\u2588\u2588\u2588\u2588\u2588\u2588\u2588\u2588\u2588\u2588\u2588\u2588\u2588\u2588","to":"jeffrey E.","to_list":[{"name":"jeffrey E.","email":"jeevacation@gmail.com"}],"cc_list":[],"subject":"Re: Fwd:","date":"2014-09-19T17:12:00.000Z","formatted_date":"Sep 19, 2014","formatted_time":"5:12 PM","body":"I think I should do it.","body_html":"<p>I think I should do it.</p>\n","is_from_epstein":false,"attachments":0,"avatar_color":"#f39c12","stars":0,"is_redacted":true},{"id":"1369","from":"jeffrey E.","from_email":"jeevacation@gmail.com","to":"Kathy Ruemmler","to_list":[{"name":"Kathy Ruemmler","email":"\u2588\u2588\u2588\u2588\u2588\u2588\u2588\u2588\u2588\u2588\u2588\u2588\u2588\u2588\u2588\u2588\u2588\u2588\u2588\u2588"}],"cc_list":[],"subject":"Re: Fwd:","date":"2014-09-19T16:12:00.000Z","formatted_date":"Sep 19, 2014","formatted_time":"4:12 PM","body":"free now","body_html":"<p>free now</p>\n","is_from_epstein":true,"attachments":0,"avatar_color":"#db4437","stars":0,"is_redacted":true},{"id":"1370","from":"Kathy Ruemmler","from_email":"\u2588\u2588\u2588\u2588\u2588\u2588\u2588\u2588\u2588\u2588\u2588\u2588\u2588\u2588\u2588\u2588\u2588\u2588\u2588\u2588","to":"jeffrey E.","to_list":[{"name":"jeffrey E.","email":"jeevacation@gmail.com"}],"cc_list":[],"subject":"Re: Fwd:","date":"2014-09-19T15:46:00.000Z","formatted_date":"Sep 19, 2014","formatted_time":"3:46 PM","body":"Correct. One time, maybe. Twice, no way.","body_html":"<p>Correct. One time, maybe. Twice, no way.</p>\n","is_from_epstein":false,"attachments":0,"avatar_color":"#f39c12","stars":1,"is_redacted":true},{"id":"1371","from":"jeffrey E.","from_email":"jeevacation@gmail.com","to":"Kathy Ruemmler","to_list":[{"name":"Kathy Ruemmler","email":"\u2588\u2588\u2588\u2588\u2588\u2588\u2588\u2588\u2588\u2588\u2588\u2588\u2588\u2588\u2588\u2588\u2588\u2588\u2588\u2588"}],"cc_list":[],"subject":"Re: Fwd:","date":"2014-09-19T15:45:00.000Z","formatted_date":"Sep 19, 2014","formatted_time":"3:45 PM","body":"of course not, he wouldnt have been so stupid.","body_html":"<p>of course not, he wouldnt have been so stupid.</p>\n","is_from_epstein":true,"attachments":0,"avatar_color":"#db4437","stars":1,"is_redacted":true},{"id":"1372","from":"Kathy Ruemmler","from_email":"\u2588\u2588\u2588\u2588\u2588\u2588\u2588\u2588\u2588\u2588\u2588\u2588\u2588\u2588\u2588\u2588\u2588\u2588\u2588\u2588","to":"jeffrey E.","to_list":[{"name":"jeffrey E.","email":"jeevacation@gmail.com"}],"cc_list":[],"subject":"Re: Fwd:","date":"2014-09-19T15:44:00.000Z","formatted_date":"Sep 19, 2014","formatted_time":"3:44 PM","body":"Gov is not jewish","body_html":"<p>Gov is not jewish</p>\n","is_from_epstein":false,"attachments":0,"avatar_color":"#f39c12","stars":5,"is_redacted":true},{"id":"1373","from":"jeffrey E.","from_email":"jeevacation@gmail.com","to":"Kathy Ruemmler","to_list":[{"name":"Kathy Ruemmler","email":"\u2588\u2588\u2588\u2588\u2588\u2588\u2588\u2588\u2588\u2588\u2588\u2588\u2588\u2588\u2588\u2588\u2588\u2588\u2588\u2588"}],"cc_list":[],"subject":"Re: Fwd:","date":"2014-09-19T15:42:00.000Z","formatted_date":"Sep 19, 2014","formatted_time":"3:42 PM","body":"reid or governor","body_html":"<p>reid or governor</p>\n","is_from_epstein":true,"attachments":0,"avatar_color":"#db4437","stars":1,"is_redacted":true},{"id":"1374","from":"Kathy Ruemmler","from_email":"\u2588\u2588\u2588\u2588\u2588\u2588\u2588\u2588\u2588\u2588\u2588\u2588\u2588\u2588\u2588\u2588\u2588\u2588\u2588\u2588","to":"jeffrey E.","to_list":[{"name":"jeffrey E.","email":"jeevacation@gmail.com"}],"cc_list":[],"subject":"Re: Fwd:","date":"2014-09-19T15:02:00.000Z","formatted_date":"Sep 19, 2014","formatted_time":"3:02 PM","body":"Uh, yeah. We will now go through a period of self-reflection and despair.","body_html":"<p>Uh, yeah. We will now go through a period of self-reflection and despair.</p>\n","is_from_epstein":false,"attachments":0,"avatar_color":"#f39c12","stars":1,"is_redacted":true},{"id":"1375","from":"jeffrey E.","from_email":"jeevacation@gmail.com","to":"Kathy Ruemmler","to_list":[{"name":"Kathy Ruemmler","email":"\u2588\u2588\u2588\u2588\u2588\u2588\u2588\u2588\u2588\u2588\u2588\u2588\u2588\u2588\u2588\u2588\u2588\u2588\u2588\u2588"}],"cc_list":[],"subject":"Re: Fwd:","date":"2014-09-19T15:00:00.000Z","formatted_date":"Sep 19, 2014","formatted_time":"3:00 PM","body":"double whoops","body_html":"<p>double whoops</p>\n","is_from_epstein":true,"attachments":0,"avatar_color":"#db4437","stars":5,"is_redacted":true},{"id":"1376","from":"Kathy Ruemmler","from_email":"\u2588\u2588\u2588\u2588\u2588\u2588\u2588\u2588\u2588\u2588\u2588\u2588\u2588\u2588\u2588\u2588\u2588\u2588\u2588\u2588","to":"jeffrey E.","to_list":[{"name":"jeffrey E.","email":"jeevacation@gmail.com"}],"cc_list":[],"subject":"Re: Fwd:","date":"2014-09-19T14:59:00.000Z","formatted_date":"Sep 19, 2014","formatted_time":"2:59 PM","body":"Yep. And now he is a repeat offender.","body_html":"<p>Yep. And now he is a repeat offender.</p>\n","is_from_epstein":false,"attachments":0,"avatar_color":"#f39c12","stars":1,"is_redacted":true},{"id":"1377","from":"jeffrey E.","from_email":"jeevacation@gmail.com","to":"Kathy Ruemmler","to_list":[{"name":"Kathy Ruemmler","email":"\u2588\u2588\u2588\u2588\u2588\u2588\u2588\u2588\u2588\u2588\u2588\u2588\u2588\u2588\u2588\u2588\u2588\u2588\u2588\u2588"}],"cc_list":[],"subject":"Re: Fwd:","date":"2014-09-19T14:58:00.000Z","formatted_date":"Sep 19, 2014","formatted_time":"2:58 PM","body":"and thats after turning down misdeameors? whoops","body_html":"<p>and thats after turning down misdeameors? whoops</p>\n","is_from_epstein":true,"attachments":0,"avatar_color":"#db4437","stars":3,"is_redacted":true},{"id":"1378","from":"Kathy Ruemmler","from_email":"\u2588\u2588\u2588\u2588\u2588\u2588\u2588\u2588\u2588\u2588\u2588\u2588\u2588\u2588\u2588\u2588\u2588\u2588\u2588\u2588","to":"jeffrey E.","to_list":[{"name":"jeffrey E.","email":"jeevacation@gmail.com"}],"cc_list":[],"subject":"Re: Fwd:","date":"2014-09-19T14:57:00.000Z","formatted_date":"Sep 19, 2014","formatted_time":"2:57 PM","body":"Reid's guy went down on all 7 counts.","body_html":"<p>Reid&#39;s guy went down on all 7 counts.</p>\n","is_from_epstein":false,"attachments":0,"avatar_color":"#f39c12","stars":0,"is_redacted":true},{"id":"1379","from":"Kathy Ruemmler","from_email":"\u2588\u2588\u2588\u2588\u2588\u2588\u2588\u2588\u2588\u2588\u2588\u2588\u2588\u2588\u2588\u2588\u2588\u2588\u2588\u2588","to":"jeffrey E.","to_list":[{"name":"jeffrey E.","email":"jeevacation@gmail.com"}],"cc_list":[],"subject":"Re: Fwd:","date":"2014-09-19T08:01:00.000Z","formatted_date":"Sep 19, 2014","formatted_time":"8:01 AM","body":"Yes, trains exist -- people ride them to get from one place to another.....germ factories, however. DC today, back in NY on Sunday morning.","body_html":"<p>Yes, trains exist -- people ride them to get from one place to another.....germ factories, however. DC today, back in NY on Sunday morning.</p>\n","is_from_epstein":false,"attachments":0,"avatar_color":"#f39c12","stars":0,"is_redacted":true},{"id":"1380","from":"jeffrey E.","from_email":"jeevacation@gmail.com","to":"Kathy Ruemmler","to_list":[{"name":"Kathy Ruemmler","email":"\u2588\u2588\u2588\u2588\u2588\u2588\u2588\u2588\u2588\u2588\u2588\u2588\u2588\u2588\u2588\u2588\u2588\u2588\u2588\u2588"}],"cc_list":[],"subject":"Re: Fwd:","date":"2014-09-19T07:57:00.000Z","formatted_date":"Sep 19, 2014","formatted_time":"7:57 AM","body":"train? yes, i will be like the emergency room doctor at lenox hill, put that crazy in room 1, gunshot in surgery, and the\n\"cook\" welll -- he can wait","body_html":"<p>train? yes, i will be like the emergency room doctor at lenox hill, put that crazy in room 1, gunshot in surgery, and the<br>&quot;cook&quot; welll -- he can wait</p>\n","is_from_epstein":true,"attachments":0,"avatar_color":"#db4437","stars":1,"is_redacted":true},{"id":"1381","from":"Kathy Ruemmler","from_email":"\u2588\u2588\u2588\u2588\u2588\u2588\u2588\u2588\u2588\u2588\u2588\u2588\u2588\u2588\u2588\u2588\u2588\u2588\u2588\u2588","to":"jeffrey E.","to_list":[{"name":"jeffrey E.","email":"jeevacation@gmail.com"}],"cc_list":[],"subject":"Re: Fwd:","date":"2014-09-19T07:54:00.000Z","formatted_date":"Sep 19, 2014","formatted_time":"7:54 AM","body":"Doesn't look like you are prioritizing your schedule very effectively.....how are you going to manage all of that? this is unga week so the boss will be in town too.....I'll be here all week -- you may get sick of me....just sat down on the train so can't talk freely.","body_html":"<p>Doesn&#39;t look like you are prioritizing your schedule very effectively.....how are you going to manage all of that? this is unga week so the boss will be in town too.....I&#39;ll be here all week -- you may get sick of me....just sat down on the train so can&#39;t talk freely.</p>\n","is_from_epstein":false,"attachments":0,"avatar_color":"#f39c12","stars":3,"is_redacted":true},{"id":"1382","from":"jeffrey E.","from_email":"jeevacation@gmail.com","to":"Kathy Ruemmler","to_list":[{"name":"Kathy Ruemmler","email":"\u2588\u2588\u2588\u2588\u2588\u2588\u2588\u2588\u2588\u2588\u2588\u2588\u2588\u2588\u2588\u2588\u2588\u2588\u2588\u2588"}],"cc_list":[],"subject":"Re: Fwd:","date":"2014-09-19T07:48:00.000Z","formatted_date":"Sep 19, 2014","formatted_time":"7:48 AM","body":"\"girls?\",, careful i will renew an old habit, this week, thiel, summers,bill burns, gordon brown, jagland, (council of europe and nobel chairman ). mongolia pres, hardeep puree ( india), boris (gates). jabor (qatar). sultan (dubai, ), kosslyn ( harvard), leon black, woody. you are a welcome guest at any..... also if you think there are interesting people in town, everyone here for climate summit, clinton security council, holy shit im on \u2588\u2588\u2588\u2588\u2588\u2588\u2588\u2588\u2588 for next 30 minutes","body_html":"<p>&quot;girls?&quot;,, careful i will renew an old habit, this week, thiel, summers,bill burns, gordon brown, jagland, (council of europe and nobel chairman ). mongolia pres, hardeep puree ( india), boris (gates). jabor (qatar). sultan (dubai, ), kosslyn ( harvard), leon black, woody. you are a welcome guest at any..... also if you think there are interesting people in town, everyone here for climate summit, clinton security council, holy shit im on \u2588\u2588\u2588\u2588\u2588\u2588\u2588\u2588\u2588 for next 30 minutes</p>\n","is_from_epstein":true,"attachments":0,"avatar_color":"#db4437","stars":20,"is_redacted":true},{"id":"1383","from":"Kathy Ruemmler","from_email":"\u2588\u2588\u2588\u2588\u2588\u2588\u2588\u2588\u2588\u2588\u2588\u2588\u2588\u2588\u2588\u2588\u2588\u2588\u2588\u2588","to":"jeffrey E.","to_list":[{"name":"jeffrey E.","email":"jeevacation@gmail.com"}],"cc_list":[],"subject":"Re: Fwd:","date":"2014-09-19T07:15:00.000Z","formatted_date":"Sep 19, 2014","formatted_time":"7:15 AM","body":"Most girls do not have to worry about this crap.","body_html":"<p>Most girls do not have to worry about this crap.</p>\n","is_from_epstein":false,"attachments":0,"avatar_color":"#f39c12","stars":2,"is_redacted":true},{"id":"1384","from":"jeffrey E.","from_email":"jeevacation@gmail.com","to":"Kathy Ruemmler","to_list":[{"name":"Kathy Ruemmler","email":"\u2588\u2588\u2588\u2588\u2588\u2588\u2588\u2588\u2588\u2588\u2588\u2588\u2588\u2588\u2588\u2588\u2588\u2588\u2588\u2588"}],"cc_list":[],"subject":"Re: Fwd:","date":"2014-09-19T07:09:00.000Z","formatted_date":"Sep 19, 2014","formatted_time":"7:09 AM","body":"understood. it comes down to high risk / reward / low risk / reward. professional, emotional. and fiinancial","body_html":"<p>understood. it comes down to high risk / reward / low risk / reward. professional, emotional. and fiinancial</p>\n","is_from_epstein":true,"attachments":0,"avatar_color":"#db4437","stars":0,"is_redacted":true},{"id":"1385","from":"Kathy Ruemmler","from_email":"\u2588\u2588\u2588\u2588\u2588\u2588\u2588\u2588\u2588\u2588\u2588\u2588\u2588\u2588\u2588\u2588\u2588\u2588\u2588\u2588","to":"jeffrey E.","to_list":[{"name":"jeffrey E.","email":"jeevacation@gmail.com"}],"cc_list":[],"subject":"Re: Fwd:","date":"2014-09-19T06:15:00.000Z","formatted_date":"Sep 19, 2014","formatted_time":"6:15 AM","body":"Agreed, but I need to be prepared to say yes before I talk to him.\n\nSent from my iPad","body_html":"<p>Agreed, but I need to be prepared to say yes before I talk to him.</p>\n<p>Sent from my iPad</p>\n","is_from_epstein":false,"attachments":0,"avatar_color":"#f39c12","stars":1,"is_redacted":true},{"id":"1386","from":"jeffrey E.","from_email":"jeevacation@gmail.com","to":"Kathy Ruemmler","to_list":[{"name":"Kathy Ruemmler","email":"\u2588\u2588\u2588\u2588\u2588\u2588\u2588\u2588\u2588\u2588\u2588\u2588\u2588\u2588\u2588\u2588\u2588\u2588\u2588\u2588"}],"cc_list":[],"subject":"Re: Fwd:","date":"2014-09-19T01:21:00.000Z","formatted_date":"Sep 19, 2014","formatted_time":"1:21 AM","body":"You need to talk to boss\n\n--\n\nplease note\n\nThe information contained in this communication is confidential, may be attorney-client privileged, may constitute inside information, and is intended only for the use of the addressee. It is the property of JEE\n\nUnauthorized use, disclosure or copying of this communication or any part thereof is strictly prohibited and may be unlawful. If you have received this communication in error, please notify us immediately by return e-mail or by e-mail to jeevacation@gmail.com, and destroy this communication and all copies thereof, including all attachments. copyright -all rights reserved","body_html":"<p>You need to talk to boss</p>\n<p>--</p>\n<p>please note</p>\n<p>The information contained in this communication is confidential, may be attorney-client privileged, may constitute inside information, and is intended only for the use of the addressee. It is the property of JEE</p>\n<p>Unauthorized use, disclosure or copying of this communication or any part thereof is strictly prohibited and may be unlawful. If you have received this communication in error, please notify us immediately by return e-mail or by e-mail to <a href=\"mailto:jeevacation@gmail.com\">jeevacation@gmail.com</a>, and destroy this communication and all copies thereof, including all attachments. copyright -all rights reserved</p>\n","is_from_epstein":true,"attachments":0,"avatar_color":"#db4437","stars":11,"is_redacted":true}]