[{"id":"3612","did":"HOUSE_OVERSIGHT_029689","f":"Jeffrey Epstein","fe":"jeevacation@gmail.com","t":"Larry Summers","s":"(no subject)","sn":"Tunisia: Tunisia's transition suffered a terrible blow on February 6th when leftist opposition a","d":"2013-02-14T20:45:00.000Z","fd":"Feb 14, 2013","ft":"8:45 PM","ep":true,"sent":true,"att":0,"ac":"#0f9d58","st":53,"r":false},{"id":"889","did":"HOUSE_OVERSIGHT_025028","f":"Jeffrey Epstein","fe":"jeevacation@gmail.com","t":"Bill Siegel","s":"Re: Fro- The Control Factor - Frontpage Magazine interview","sn":"SAAAAAAAAAAAFe good boy","d":"2013-02-08T21:05:00.000Z","fd":"Feb 8, 2013","ft":"9:05 PM","ep":true,"sent":true,"att":1,"ac":"#0f9d58","st":29,"r":true},{"id":"917","did":"HOUSE_OVERSIGHT_024419","f":"Bill Siegel","fe":"\u2588\u2588\u2588\u2588\u2588\u2588\u2588\u2588\u2588\u2588\u2588\u2588\u2588","t":"jeevacation@gmail.com","s":"Re: Fro- The Control Factor - Frontpage Magazine interview","sn":"Stillllllllllllll just engaged. I meant shirley","d":"2013-02-08T21:02:00.000Z","fd":"Feb 8, 2013","ft":"9:02 PM","ep":false,"sent":true,"att":1,"ac":"#f39c12","st":9,"r":true},{"id":"754","did":"HOUSE_OVERSIGHT_024407","f":"Bill Siegel","fe":"\u2588","t":"jeevacation@gmail.com","s":"Re: Fro- The Control Factor - Frontpage Magazine interview","sn":"I will let you know when I go back. Do you know her?","d":"2013-02-08T20:48:00.000Z","fd":"Feb 8, 2013","ft":"8:48 PM","ep":false,"sent":true,"att":1,"ac":"#f39c12","st":7,"r":true},{"id":"951","did":"HOUSE_OVERSIGHT_024395","f":"Bill Siegel","fe":"\u2588\u2588\u2588\u2588\u2588\u2588\u2588\u2588\u2588\u2588\u2588\u2588\u2588\u2588\u2588","t":"jeevacation@gmail.com","s":"Re: Fro- The Control Factor - Frontpage Magazine interview","sn":"You ok? I became friendly with shirley maclaine last year and went to her ranch in sante fe. I may g","d":"2013-02-08T20:10:00.000Z","fd":"Feb 8, 2013","ft":"8:10 PM","ep":false,"sent":true,"att":1,"ac":"#f39c12","st":12,"r":true},{"id":"950","did":"HOUSE_OVERSIGHT_024384","f":"Bill Siegel","fe":"\u2588\u2588\u2588\u2588\u2588\u2588\u2588\u2588\u2588\u2588\u2588\u2588\u2588","t":"Charlotte Abrams","s":"Fro- The Control Factor - Frontpage Magazine interview","sn":"Bill Siegel hopes this might be of interest to you: http://frontpagemag.com/2013/jamie-glazov/the-co","d":"2013-02-08T19:40:00.000Z","fd":"Feb 8, 2013","ft":"7:40 PM","ep":false,"sent":false,"att":1,"ac":"#f39c12","st":19,"r":true},{"id":"888","did":"HOUSE_OVERSIGHT_025028","f":"Bill Siegel","fe":"\u2588\u2588\u2588\u2588\u2588\u2588\u2588\u2588\u2588\u2588\u2588\u2588\u2588\u2588","t":"Jeffrey Epstein","s":"Re: Fro- The Control Factor - Frontpage Magazine interview","sn":"Still\u2588\u2588\u2588\u2588\u2588\u2588\u2588\u2588\u2588\u2588\u2588\u2588\u2588 just engaged. I meant shirley","d":"2013-02-08T17:02:00.000Z","fd":"Feb 8, 2013","ft":"5:02 PM","ep":false,"sent":true,"att":0,"ac":"#9c27b0","st":1,"r":true},{"id":"919","did":"HOUSE_OVERSIGHT_024419","f":"Bill Siegel","fe":"\u2588\u2588\u2588\u2588\u2588\u2588\u2588\u2588\u2588\u2588\u2588\u2588\u2588","t":"Jeffrey Epstein","s":"Re: Fro- The Control Factor - Frontpage Magazine interview","sn":"I will let you know when I go back. Do you know her?","d":"2013-02-08T16:48:00.000Z","fd":"Feb 8, 2013","ft":"4:48 PM","ep":false,"sent":true,"att":0,"ac":"#f39c12","st":0,"r":true},{"id":"886","did":"HOUSE_OVERSIGHT_025028","f":"Bill Siegel","fe":"\u2588\u2588\u2588\u2588\u2588\u2588\u2588\u2588\u2588\u2588\u2588\u2588\u2588\u2588","t":"Jeffrey Epstein","s":"Re: Fro- The Control Factor - Frontpage Magazine interview","sn":"I will let you know when I go back. Do you know her?","d":"2013-02-08T16:48:00.000Z","fd":"Feb 8, 2013","ft":"4:48 PM","ep":false,"sent":true,"att":0,"ac":"#9c27b0","st":0,"r":true},{"id":"756","did":"HOUSE_OVERSIGHT_024407","f":"Bill Siegel","fe":"\u2588\u2588\u2588\u2588\u2588\u2588\u2588\u2588\u2588","t":"Jeffrey Epstein","s":"Re: Fro- The Control Factor - Frontpage Magazine interview","sn":"You ok? I became friendly with shirley maclaine last year and went to her ranch in sante fe. I may g","d":"2013-02-08T16:10:00.000Z","fd":"Feb 8, 2013","ft":"4:10 PM","ep":false,"sent":true,"att":0,"ac":"#f39c12","st":0,"r":true},{"id":"921","did":"HOUSE_OVERSIGHT_024419","f":"Bill Siegel","fe":"\u2588\u2588\u2588\u2588\u2588\u2588\u2588\u2588\u2588\u2588\u2588\u2588\u2588","t":"Jeffrey Epstein","s":"Re: Fro- The Control Factor - Frontpage Magazine interview","sn":"You ok? I became friendly with shirley maclaine last year and went to her ranch in sante fe. I may g","d":"2013-02-08T16:10:00.000Z","fd":"Feb 8, 2013","ft":"4:10 PM","ep":false,"sent":true,"att":0,"ac":"#f39c12","st":0,"r":true},{"id":"884","did":"HOUSE_OVERSIGHT_025028","f":"Bill Siegel","fe":"\u2588\u2588\u2588\u2588\u2588\u2588\u2588\u2588\u2588\u2588\u2588\u2588\u2588\u2588","t":"Jeffrey Epstein","s":"Re: Fro- The Control Factor - Frontpage Magazine interview","sn":"You ok? I became friendly with shirley maclaine last year and went to her ranch in sante fe. I may g","d":"2013-02-08T16:10:00.000Z","fd":"Feb 8, 2013","ft":"4:10 PM","ep":false,"sent":true,"att":0,"ac":"#9c27b0","st":1,"r":true},{"id":"918","did":"HOUSE_OVERSIGHT_024419","f":"Jeffrey Epstein","fe":"jeevacation@gmail.com","t":"Bill Siegel","s":"Re: Fro- The Control Factor - Frontpage Magazine interview","sn":"shirley or your wife","d":"2013-02-08T15:49:00.000Z","fd":"Feb 8, 2013","ft":"3:49 PM","ep":true,"sent":true,"att":0,"ac":"#0f9d58","st":2,"r":false},{"id":"887","did":"HOUSE_OVERSIGHT_025028","f":"Jeffrey Epstein","fe":"jeevacation@gmail.com","t":"Bill Siegel","s":"Re: Fro- The Control Factor - Frontpage Magazine interview","sn":"shirley or your wife","d":"2013-02-08T15:49:00.000Z","fd":"Feb 8, 2013","ft":"3:49 PM","ep":true,"sent":true,"att":0,"ac":"#0f9d58","st":4,"r":false},{"id":"953","did":"HOUSE_OVERSIGHT_024395","f":"Bill Siegel","fe":"\u2588\u2588\u2588\u2588\u2588\u2588\u2588\u2588\u2588\u2588\u2588\u2588\u2588\u2588\u2588","t":"Jeffrey Epstein","s":"Re: Fro- The Control Factor - Frontpage Magazine interview","sn":"Bill Siegel hopes this might be of interest to you: http://frontpagemag.com/2013/jamie-glazov/the-co","d":"2013-02-08T15:40:00.000Z","fd":"Feb 8, 2013","ft":"3:40 PM","ep":false,"sent":true,"att":0,"ac":"#f39c12","st":28,"r":true},{"id":"758","did":"HOUSE_OVERSIGHT_024407","f":"Bill Siegel","fe":"\u2588\u2588\u2588\u2588\u2588\u2588\u2588\u2588\u2588","t":"Jeffrey Epstein","s":"Re: Fro- The Control Factor - Frontpage Magazine interview","sn":"Bill Siegel hopes this might be of interest to you: http://frontpagemag.com/2013/jamie-glazov/the-co","d":"2013-02-08T15:40:00.000Z","fd":"Feb 8, 2013","ft":"3:40 PM","ep":false,"sent":true,"att":0,"ac":"#f39c12","st":4,"r":true},{"id":"923","did":"HOUSE_OVERSIGHT_024419","f":"Bill Siegel","fe":"\u2588\u2588\u2588\u2588\u2588\u2588\u2588\u2588\u2588\u2588\u2588\u2588\u2588","t":"Jeffrey Epstein","s":"Re: Fro- The Control Factor - Frontpage Magazine interview","sn":"Bill Siegel hopes this might be of interest to you: http://frontpagemag.com/2013/jamie-glazov/the-co","d":"2013-02-08T15:40:00.000Z","fd":"Feb 8, 2013","ft":"3:40 PM","ep":false,"sent":true,"att":0,"ac":"#f39c12","st":10,"r":true},{"id":"882","did":"HOUSE_OVERSIGHT_025028","f":"Bill Siegel","fe":"\u2588\u2588\u2588\u2588\u2588\u2588\u2588\u2588\u2588\u2588\u2588\u2588\u2588\u2588","t":"Jeffrey Epstein","s":"Re: Fro- The Control Factor - Frontpage Magazine interview","sn":"Bill Siegel hopes this might be of interest to you: http://frontpagemag.com/2013/jamie-glazov/the-co","d":"2013-02-08T15:40:00.000Z","fd":"Feb 8, 2013","ft":"3:40 PM","ep":false,"sent":true,"att":0,"ac":"#9c27b0","st":8,"r":true},{"id":"755","did":"HOUSE_OVERSIGHT_024407","f":"Jeffrey Epstein","fe":"jeevacation@gmail.com","t":"Bill Siegel","s":"Re: Fro- The Control Factor - Frontpage Magazine interview","sn":"great. place.. when will you go.. did you get married? i m between alber and santa fe,, zorrro ranch","d":"2013-02-08T15:16:00.000Z","fd":"Feb 8, 2013","ft":"3:16 PM","ep":true,"sent":true,"att":0,"ac":"#0f9d58","st":2,"r":false},{"id":"920","did":"HOUSE_OVERSIGHT_024419","f":"Jeffrey Epstein","fe":"jeevacation@gmail.com\u2588","t":"Bill Siegel","s":"Re: Fro- The Control Factor - Frontpage Magazine interview","sn":"great. place.. when will you go.. did you get married? im between alber and santa fe,, zorrro ranch,","d":"2013-02-08T15:16:00.000Z","fd":"Feb 8, 2013","ft":"3:16 PM","ep":true,"sent":true,"att":0,"ac":"#673ab7","st":1,"r":true},{"id":"885","did":"HOUSE_OVERSIGHT_025028","f":"Jeffrey Epstein","fe":"jeevacation@gmail.com","t":"Bill Siegel","s":"Re: Fro- The Control Factor - Frontpage Magazine interview","sn":"great. place.. when will you go.. did you get married? i m between alber and santa fe,, zorrro ranch","d":"2013-02-08T15:16:00.000Z","fd":"Feb 8, 2013","ft":"3:16 PM","ep":true,"sent":true,"att":0,"ac":"#0f9d58","st":3,"r":false},{"id":"952","did":"HOUSE_OVERSIGHT_024395","f":"Jeffrey Epstein","fe":"jeevacation@gmail.com","t":"Bill Siegel","s":"Re: Fro- The Control Factor - Frontpage Magazine interview","sn":"I already rad it. congragulations hope to see you soon    The information contained in this commu","d":"2013-02-08T14:58:00.000Z","fd":"Feb 8, 2013","ft":"2:58 PM","ep":true,"sent":true,"att":0,"ac":"#0f9d58","st":7,"r":false},{"id":"757","did":"HOUSE_OVERSIGHT_024407","f":"Jeffrey Epstein","fe":"jeevacation@gmail.com","t":"Bill Siegel","s":"Re: Fro- The Control Factor - Frontpage Magazine interview","sn":"I already rad it. congragulations hope to see you soon","d":"2013-02-08T14:58:00.000Z","fd":"Feb 8, 2013","ft":"2:58 PM","ep":true,"sent":true,"att":0,"ac":"#0f9d58","st":0,"r":false},{"id":"922","did":"HOUSE_OVERSIGHT_024419","f":"Jeffrey Epstein","fe":"jeevacation@gmail.com","t":"Bill Siegel","s":"Re: Fro- The Control Factor - Frontpage Magazine interview","sn":"I already rad it. congragulations hope to see you soon","d":"2013-02-08T14:58:00.000Z","fd":"Feb 8, 2013","ft":"2:58 PM","ep":true,"sent":true,"att":0,"ac":"#0f9d58","st":1,"r":false},{"id":"883","did":"HOUSE_OVERSIGHT_025028","f":"Jeffrey Epstein","fe":"jeevacation@gmail.com","t":"Bill Siegel","s":"Re: Fro- The Control Factor - Frontpage Magazine interview","sn":"I already rad it. congragulations hope to see you soon","d":"2013-02-08T14:58:00.000Z","fd":"Feb 8, 2013","ft":"2:58 PM","ep":true,"sent":true,"att":0,"ac":"#0f9d58","st":5,"r":false},{"id":"411","did":"HOUSE_OVERSIGHT_022258","f":"Jeffrey Epstein","fe":"jeevacation@gmail.com","t":"\u2588\u2588\u2588\u2588\u2588","s":"Re:","sn":"yes but with a 2.2 billion dollar top. most planes are above 100 each, hence the issue  ","d":"2013-01-31T11:37:00.000Z","fd":"Jan 31, 2013","ft":"11:37 AM","ep":true,"sent":true,"att":0,"ac":"#0f9d58","st":23,"r":true},{"id":"405","did":"HOUSE_OVERSIGHT_022214","f":"\u2588","fe":"\u2588","t":"Jeffrey Epstein","s":"Re:","sn":"Apparently Brazil is a hot investment place now (?) It is more about the offset part than the jet de","d":"2013-01-31T11:32:00.000Z","fd":"Jan 31, 2013","ft":"11:32 AM","ep":false,"sent":true,"att":0,"ac":"#db4437","st":17,"r":true},{"id":"410","did":"HOUSE_OVERSIGHT_022258","f":"\u2588","fe":"\u2588","t":"Jeffrey Epstein","s":"Re:","sn":"Apparently Brazil is a hot investment place now (?) It is more about the offset part than the jet de","d":"2013-01-31T07:32:00.000Z","fd":"Jan 31, 2013","ft":"7:32 AM","ep":false,"sent":true,"att":0,"ac":"#db4437","st":6,"r":true},{"id":"404","did":"HOUSE_OVERSIGHT_022214","f":"\u2588","fe":"\u2588","t":"Jeffrey Epstein","s":"Re:","sn":"Hmm, so the offset service provider does what - negotiation between the parties? Complex sounds inte","d":"2013-01-31T06:36:00.000Z","fd":"Jan 31, 2013","ft":"6:36 AM","ep":false,"sent":true,"att":0,"ac":"#db4437","st":0,"r":true},{"id":"408","did":"HOUSE_OVERSIGHT_022258","f":"Nadia","fe":"\u2588\u2588\u2588\u2588\u2588\u2588\u2588\u2588\u2588\u2588\u2588","t":"Jeffrey Epstein","s":"Re:","sn":"Hmm, so the offset service provider does what - negotiation between the parties? Complex sounds inte","d":"2013-01-31T06:36:00.000Z","fd":"Jan 31, 2013","ft":"6:36 AM","ep":false,"sent":true,"att":0,"ac":"#4285f4","st":5,"r":true},{"id":"403","did":"HOUSE_OVERSIGHT_022214","f":"Jeffrey Epstein","fe":"jeevacation@gmail.com","t":"\u2588\u2588\u2588\u2588\u2588\u2588\u2588\u2588\u2588\u2588\u2588","s":"Re:","sn":"brazil, has tried to buy fighters, in the past, they don't have a lot of money,","d":"2013-01-31T05:47:00.000Z","fd":"Jan 31, 2013","ft":"5:47 AM","ep":true,"sent":true,"att":0,"ac":"#0f9d58","st":4,"r":true},{"id":"409","did":"HOUSE_OVERSIGHT_022258","f":"Jeffrey Epstein","fe":"jeevacation@gmail.com","t":"\u2588\u2588\u2588\u2588\u2588\u2588\u2588\u2588\u2588\u2588\u2588","s":"Re:","sn":"brazil , has tried to buy fighters, in the past, they don't have a lot of money,  ","d":"2013-01-31T05:47:00.000Z","fd":"Jan 31, 2013","ft":"5:47 AM","ep":true,"sent":true,"att":0,"ac":"#0f9d58","st":10,"r":true},{"id":"402","did":"HOUSE_OVERSIGHT_022214","f":"Jeffrey Epstein","fe":"jeevacation@gmail.com","t":"\u2588\u2588\u2588\u2588\u2588\u2588\u2588\u2588\u2588","s":"Re:","sn":"Yes, one of the most complex negotiations they re very strange. Someone buys fighters but with the f","d":"2013-01-31T03:36:00.000Z","fd":"Jan 31, 2013","ft":"3:36 AM","ep":true,"sent":true,"att":0,"ac":"#0f9d58","st":26,"r":true},{"id":"407","did":"HOUSE_OVERSIGHT_022258","f":"Jeffrey Epstein","fe":"jeevacation@gmail.com","t":"\u2588\u2588\u2588\u2588\u2588\u2588\u2588\u2588\u2588","s":"Re:","sn":"Yes, one of the most complex negotiations they re very strange. Someone buys fighters but with the f","d":"2013-01-31T03:36:00.000Z","fd":"Jan 31, 2013","ft":"3:36 AM","ep":true,"sent":true,"att":0,"ac":"#0f9d58","st":55,"r":true},{"id":"401","did":"HOUSE_OVERSIGHT_022214","f":"\u2588","fe":"\u2588","t":"Jeffrey Epstein","s":"Re:","sn":"Do you understand offset agreements? I got asked to be involved in negotiating some of the deals bet","d":"2013-01-31T00:00:00.000Z","fd":"Jan 31, 2013","ft":"12:00 AM","ep":false,"sent":true,"att":0,"ac":"#db4437","st":8,"r":true},{"id":"406","did":"HOUSE_OVERSIGHT_022258","f":"\u2588","fe":"\u2588","t":"Jeffrey Epstein","s":"Re:","sn":"Do you understand offset agreements? I got asked to be involved in negotiating some of the deals bet","d":"2013-01-31T00:00:00.000Z","fd":"Jan 31, 2013","ft":"12:00 AM","ep":false,"sent":true,"att":0,"ac":"#db4437","st":16,"r":true},{"id":"2400","did":"HOUSE_OVERSIGHT_026580","f":"Cecile de Jongh","fe":"\u2588\u2588\u2588\u2588\u2588\u2588\u2588\u2588\u2588\u2588\u2588\u2588\u2588\u2588\u2588\u2588","t":"JEE","s":"Antigua: Land Of Sun, Sand, And Super Cheap Downloads","sn":" Antigua: Land Of Sun, Sand, And Super Cheap Downloads  by Jacob Goldstein [http://www.npr.org/bl","d":"2013-01-29T16:46:00.000Z","fd":"Jan 29, 2013","ft":"4:46 PM","ep":false,"sent":false,"att":0,"ac":"#db4437","st":14,"r":true},{"id":"3723","did":"HOUSE_OVERSIGHT_029684","f":"Jeffrey Epstein","fe":"jeevacation@gmail.com","t":"Mohamed Waheed","s":"Re:","sn":"can we speak today, ?","d":"2013-01-29T12:06:00.000Z","fd":"Jan 29, 2013","ft":"12:06 PM","ep":true,"sent":true,"att":0,"ac":"#0f9d58","st":14,"r":true},{"id":"3579","did":"HOUSE_OVERSIGHT_029534","f":"Jeffrey Epstein","fe":"jeevacation@gmail.com","t":"Mohamed Waheed Hassan","s":"Re:","sn":"this from a fraud web site, your mimister will get upset that you dont want to at least try, what do","d":"2013-01-27T09:29:00.000Z","fd":"Jan 27, 2013","ft":"9:29 AM","ep":true,"sent":true,"att":0,"ac":"#0f9d58","st":12,"r":true},{"id":"3725","did":"HOUSE_OVERSIGHT_029684","f":"Jeffrey Epstein","fe":"jeevacation@gmail.com","t":"Mohamed Waheed","s":"Re:","sn":"this from a fraud web site, your mimister will get upset that you dont want to at least try, what do","d":"2013-01-27T09:29:00.000Z","fd":"Jan 27, 2013","ft":"9:29 AM","ep":true,"sent":true,"att":0,"ac":"#0f9d58","st":8,"r":true},{"id":"3578","did":"HOUSE_OVERSIGHT_029534","f":"Mohamed Waheed","fe":"\u2588\u2588\u2588\u2588\u2588\u2588\u2588\u2588\u2588\u2588\u2588\u2588\u2588\u2588\u2588\u2588","t":"Jeffrey Epstein","s":"Re:","sn":"Thank you. You are my savior. I will do exactly what you said.  Sent from my iPhone","d":"2013-01-27T04:33:00.000Z","fd":"Jan 27, 2013","ft":"4:33 AM","ep":false,"sent":true,"att":0,"ac":"#4285f4","st":3,"r":true},{"id":"3720","did":"HOUSE_OVERSIGHT_029680","f":"Jeffrey Epstein","fe":"jeevacation@gmail.com","t":"Mohamed Waheed Hassan \u2588\u2588\u2588\u2588\u2588\u2588\u2588\u2588\u2588\u2588\u2588\u2588\u2588\u2588\u2588\u2588","s":"Re:","sn":"it is a scam.. what they willl tell you is the only thing they want is a vehicle and a bank acct and","d":"2013-01-27T04:15:00.000Z","fd":"Jan 27, 2013","ft":"4:15 AM","ep":true,"sent":true,"att":1,"ac":"#0f9d58","st":19,"r":true},{"id":"3588","did":"HOUSE_OVERSIGHT_029530","f":"Mohamed Waheed Hassan","fe":"\u2588\u2588\u2588\u2588\u2588\u2588\u2588\u2588\u2588\u2588\u2588\u2588\u2588\u2588\u2588\u2588\u2588\u2588\u2588\u2588","t":"Jeffrey Epstein","s":"Re:","sn":"Jeffrey, Need your advice. My finance minister is telling me that he has an anonymous funds manager ","d":"2013-01-27T03:49:00.000Z","fd":"Jan 27, 2013","ft":"3:49 AM","ep":false,"sent":true,"att":0,"ac":"#673ab7","st":22,"r":true},{"id":"3724","did":"HOUSE_OVERSIGHT_029684","f":"Mohamed Waheed","fe":"\u2588\u2588\u2588\u2588\u2588\u2588\u2588\u2588\u2588\u2588\u2588\u2588\u2588\u2588","t":"Jeffrey Epstein","s":"Re:","sn":"Thank you. You are my savior. I will do exactly what you said.  Sent from my iPhone","d":"2013-01-27T00:33:00.000Z","fd":"Jan 27, 2013","ft":"12:33 AM","ep":false,"sent":true,"att":0,"ac":"#4285f4","st":2,"r":true},{"id":"3580","did":"HOUSE_OVERSIGHT_029534","f":"Mohamed Waheed Hassan","fe":"\u2588\u2588\u2588\u2588\u2588\u2588\u2588\u2588\u2588\u2588","t":"Jeffrey Epstein","s":"Re:","sn":"Jeffrey, Need your advice.  My finance minister is telling me that he has an anonymous funds manager","d":"2013-01-26T22:49:00.000Z","fd":"Jan 26, 2013","ft":"10:49 PM","ep":false,"sent":true,"att":0,"ac":"#673ab7","st":11,"r":true},{"id":"3719","did":"HOUSE_OVERSIGHT_029680","f":"Mohamed Waheed Hassan","fe":"\u2588\u2588\u2588\u2588\u2588\u2588\u2588\u2588\u2588\u2588\u2588\u2588\u2588\u2588\u2588\u2588\u2588\u2588\u2588\u2588\u2588\u2588","t":"Jeffrey Epstein","s":"Re:","sn":"Jeffrey, Need your advice.  My finance minister is telling me that he has an anonymous funds manager","d":"2013-01-26T22:49:00.000Z","fd":"Jan 26, 2013","ft":"10:49 PM","ep":false,"sent":true,"att":0,"ac":"#673ab7","st":4,"r":true},{"id":"3726","did":"HOUSE_OVERSIGHT_029684","f":"Mohamed Waheed Hassan","fe":"\u2588\u2588\u2588\u2588\u2588\u2588\u2588\u2588\u2588\u2588\u2588\u2588\u2588\u2588\u2588","t":"Jeffrey Epstein","s":"Re:","sn":"Jeffrey,  Need your advice. My finance minister is telling me that he has an anonymous funds manager","d":"2013-01-26T22:49:00.000Z","fd":"Jan 26, 2013","ft":"10:49 PM","ep":false,"sent":true,"att":0,"ac":"#0f9d58","st":10,"r":true},{"id":"3735","did":"HOUSE_OVERSIGHT_029968","f":"\u2588","fe":"\u2588","t":"jeevacation@gmail.com","s":"Tom McMillen","sn":"Hi Jeffrey,  I saw Tom McMillen last night and he asked about you - said he lost touch. He's tight w","d":"2013-01-22T22:45:00.000Z","fd":"Jan 22, 2013","ft":"10:45 PM","ep":false,"sent":false,"att":0,"ac":"#db4437","st":17,"r":true},{"id":"7329","did":"HOUSE_OVERSIGHT_031120","f":"\u2588","fe":"\u2588","t":"jeevacation@gmail.com","s":"Tom McMillen","sn":"Hi Jeffrey,  I saw Tom McMillen last night and he asked about you - said he lost touch. He's tight w","d":"2013-01-22T22:45:00.000Z","fd":"Jan 22, 2013","ft":"10:45 PM","ep":false,"sent":false,"att":0,"ac":"#db4437","st":19,"r":true},{"id":"3589","did":"HOUSE_OVERSIGHT_029530","f":"Jeffrey Epstein","fe":"jeevacation@gmail.com","t":"\u2588","s":"Re:","sn":"as chairman of the council of europe , he is really mr human rights, Im sure that if he can be of he","d":"2013-01-18T17:06:00.000Z","fd":"Jan 18, 2013","ft":"5:06 PM","ep":true,"sent":true,"att":0,"ac":"#0f9d58","st":4,"r":true}]